rsap2p/__init__.py
rsap2p/_config.py
rsap2p/_cui.py
rsap2p/_myssh.py
rsap2p/_obj.py
rsap2p/_p2p.py
rsap2p/_sc.py
rsap2p/_ssh.py
rsap2p/_tcp.py
rsap2p-0.0.1.dist-info/LICENSE
rsap2p-0.0.1.dist-info/LICENSE_rsa
rsap2p-0.0.1.dist-info/METADATA
rsap2p-0.0.1.dist-info/WHEEL
rsap2p-0.0.1.dist-info/top_level.txt
rsap2p-0.0.1.dist-info/RECORD
