Metadata-Version: 2.1
Name: rsap2p
Version: 0.0.1
Summary: Decentralized end-to-end encrypted communication tool.
Home-page: https://github.com/userElaina
Author: userElaina
Author-email: userElaina@google.com
License: UNKNOWN
Project-URL: Source, https://github.com/userElaina/rsap2p
Keywords: userelaina
Platform: UNKNOWN
Classifier: License :: OSI Approved :: MIT License
Classifier: Programming Language :: Python :: 3
Classifier: Programming Language :: Python :: 3.7
Classifier: Programming Language :: Python :: 3.8
Classifier: Programming Language :: Python :: 3.9
Requires-Python: >=3.6
License-File: LICENSE
License-File: LICENSE_rsa
Requires-Dist: rsa
Requires-Dist: userelaina (==0.0.4)
